{
  "output": {
    "filePath": "ai-context/main-app-context.txt",
    "style": "markdown",
    "headerText": "Main Application context including shared libraries and layers",
    "showLineNumbers": true,
    "topFilesLength": 10
  },
  "include": [
    "apps/main-app/**/*.{ts,tsx,js,jsx,vue}",
    "apps/main-app/**/*.md",
    "libs/**/*.{ts,tsx,js}",
    "layers/**/*.{ts,tsx,js,vue}",
    "shared-runtime.config.ts"
  ],
  "ignore": {
    "useGitignore": true,
    "useDefaultPatterns": true,
    "customPatterns": [
      "**/node_modules/**",
      "**/dist/**",
      "**/coverage/**",
      "**/.nuxt/**",
      "**/tests/**",
      "**/*.test.*",
      "**/*.spec.*",
      "**/debug/**"
    ]
  },
  "security": {
    "enableSecurityCheck": true
  }
}
